reCaptchaBypasser/__init__.py
reCaptchaBypasser/setup.py
reCaptchaBypasser-1.4.dist-info/METADATA
reCaptchaBypasser-1.4.dist-info/WHEEL
reCaptchaBypasser-1.4.dist-info/top_level.txt
reCaptchaBypasser-1.4.dist-info/RECORD
