Metadata-Version: 2.1
Name: reCaptchaBypasser
Version: 1.4
Summary: This Package For Bypassing Any reCaptcha in Python .
Home-page: https://github.com/DrLinuxOfficial/reCaptchaBypasser-Py
Author: Dr.Linux
